pywoe/__init__.py
pywoe/constants.py
pywoe/interface.py
pywoe/data_models/__init__.py
pywoe/data_models/base.py
pywoe/data_models/binning.py
pywoe/data_models/feature.py
pywoe/data_models/utils.py
pywoe/data_models/woe.py
pywoe/feature_engineering/__init__.py
pywoe/feature_engineering/binning.py
pywoe/feature_engineering/utils.py
pywoe/feature_engineering/validator.py
pywoe/feature_engineering/woe.py
tests/__init__.py
tests/integration/__init__.py
tests/integration/test_custom_pipeline.py
tests/integration/test_interface.py
tests/unit/__init__.py
tests/unit/test_data_model_constructs.py
tests/unit/test_data_model_primitives.py
pywoe-0.0.2.dist-info/LICENSE
pywoe-0.0.2.dist-info/METADATA
pywoe-0.0.2.dist-info/WHEEL
pywoe-0.0.2.dist-info/top_level.txt
pywoe-0.0.2.dist-info/RECORD
