Metadata-Version: 2.1
Name: pywoe
Version: 0.0.2
Summary: The missing scikit-learn addition to work with Weight-of-Evidence scoring.
Home-page: https://github.com/pyscoring/pywoe
Author: pyscoring
Author-email: tadas.krisciunas@gmail.com
License: UNKNOWN
Platform: UNKNOWN
Classifier: Programming Language :: Python :: 3
Requires-Python: >=3.6
Requires-Dist: numpy (==1.17.3)
Requires-Dist: scipy (==1.3.3)
Requires-Dist: scikit-learn (==0.23.2)
Requires-Dist: pandas (==0.25.2)
Requires-Dist: attrs (==20.2.0)
Requires-Dist: nose (==1.3.7)
Requires-Dist: statsmodels (==0.12.0)
Requires-Dist: cattrs (==1.0.0)
